__init__.py
sz_datasets.py
sz_datasets-0.0.6.dist-info/LICENSE
sz_datasets-0.0.6.dist-info/METADATA
sz_datasets-0.0.6.dist-info/WHEEL
sz_datasets-0.0.6.dist-info/top_level.txt
sz_datasets-0.0.6.dist-info/RECORD
