Metadata-Version: 2.1
Name: sz-datasets
Version: 0.0.6
Summary: sz_datasets package
Project-URL: Homepage, https://github.com/skillzilla/sz_datasets
Project-URL: Bug Tracker, https://github.com/skillzilla/sz_datasets/issues
Classifier: Programming Language :: Python :: 3
Classifier: License :: OSI Approved :: MIT License
Classifier: Operating System :: OS Independent
Requires-Python: >=3.7
License-File: LICENSE
